kirlab_hil/__init__.py
kirlab_hil/kirlab_hil.py
kirlab_hil-0.0.2.dist-info/LICENSE
kirlab_hil-0.0.2.dist-info/METADATA
kirlab_hil-0.0.2.dist-info/WHEEL
kirlab_hil-0.0.2.dist-info/top_level.txt
kirlab_hil-0.0.2.dist-info/RECORD
