Metadata-Version: 2.1
Name: kirlab_hil
Version: 0.0.2
Summary: API wrapper for the KirLab device management
Author-email: Cesar Ruano <cesar.ruano@kirlab.com>
Project-URL: Homepage, https://kirlab.com
Classifier: Programming Language :: Python :: 3
Classifier: License :: Other/Proprietary License
Classifier: Operating System :: OS Independent
Requires-Python: >=3.7
License-File: LICENSE
